HitBTCMonster
