Metadata-Version: 1.1
Name: HitBTCMonster
Version: 0.0.3
Summary: A library for better communication with HitBTC Exchange API
Home-page: https://github.com/prscodx/HitBTCMonster
Author: {'name': 'prscodx', 'email': 'prscodx@gmail.com'}
Author-email: UNKNOWN
License: MIT
Project-URL: Source, https://github.com/prscodx/HitBTCMonster.git
Keywords: HitBTC,WSS,API
Platform: UNKNOWN
Classifier: License :: OSI Approved :: MIT License
Classifier: Programming Language :: Python :: 3
Classifier: Programming Language :: Python :: 3.4
Classifier: Programming Language :: Python :: 3.5
Classifier: Programming Language :: Python :: 3.6
Classifier: Programming Language :: Python :: 3.7
